{"version":3,"kind":"Article","sha256":"9d99a60375c76529d1dfa44ced406f67eea3f11bfa6080c88a27125689aef840","slug":"qtcloud-aigc","location":"/archive/roadmap/products/qtcloud/qtcloud-aigc.md","dependencies":[],"frontmatter":{"title":"AIGC云","content_includes_title":false,"github":"https://github.com/quanttide/quanttide-tech","keywords":["quanttide","documentation"],"numbering":{"title":{"offset":4}},"source_url":"https://github.com/quanttide/quanttide-tech/blob/main/docs/archive/roadmap/products/qtcloud/qtcloud-aigc.md","edit_url":"https://github.com/quanttide/quanttide-tech/edit/main/docs/archive/roadmap/products/qtcloud/qtcloud-aigc.md","exports":[{"format":"md","filename":"qtcloud-aigc.md","url":"/qtcloud-aigc-29cb0a81341f6e2aeeb326c88f74e0f9.md"}]},"mdast":{"type":"root","children":[{"type":"block","children":[{"type":"paragraph","position":{"start":{"line":3,"column":1},"end":{"line":3,"column":1}},"children":[{"type":"text","value":"AIGC云是一个集成了生成式人工智能技术的云服务平台。它可以帮助企业和开发人员轻松地创建、部署和管理AI生成的内容和智能体。AIGC云的主要目标是提供一个完整的解决方案，包括底层的大模型训练和顶层的应用开发，以满足中小团队的需求。","position":{"start":{"line":3,"column":1},"end":{"line":3,"column":1}},"key":"VhtEw0lUqB"}],"key":"auKuHxKQOw"},{"type":"paragraph","position":{"start":{"line":5,"column":1},"end":{"line":5,"column":1}},"children":[{"type":"text","value":"待解决问题：","position":{"start":{"line":5,"column":1},"end":{"line":5,"column":1}},"key":"A8WTG2yHBr"}],"key":"kMYzU1FWYc"},{"type":"list","ordered":false,"spread":false,"position":{"start":{"line":7,"column":1},"end":{"line":9,"column":1}},"children":[{"type":"listItem","spread":true,"position":{"start":{"line":7,"column":1},"end":{"line":7,"column":1}},"children":[{"type":"paragraph","children":[{"type":"text","value":"避免竞争：是否希望通过专注于Agent云来避免与其他竞争对手（如Dify）直接竞争？如果这是主要考虑，那么将AIGC云定位为纯粹的Agent云可能是一个合理的选择。","position":{"start":{"line":7,"column":1},"end":{"line":7,"column":1}},"key":"xOxx7fslKT"}],"key":"a1zAlII4ks"}],"key":"dLyFNOupnO"},{"type":"listItem","spread":true,"position":{"start":{"line":8,"column":1},"end":{"line":8,"column":1}},"children":[{"type":"paragraph","children":[{"type":"text","value":"补充功能：是否认为市场上缺乏某些功能，而您的AIGC云可以填补这些空白？如果是这样，那么将AIGC云定位为All in One的智能员工助手可能更加合适，因为它可以提供更全面的功能和服务。","position":{"start":{"line":8,"column":1},"end":{"line":8,"column":1}},"key":"cEEOdl1yvp"}],"key":"PC0wgOgSDx"}],"key":"mIjIe9IKxp"},{"type":"listItem","spread":true,"position":{"start":{"line":9,"column":1},"end":{"line":9,"column":1}},"children":[{"type":"paragraph","children":[{"type":"text","value":"灵活性和扩展性：是否希望AIGC云能够与其他云服务平台和应用无缝集成？如果是这样，将AIGC云设计为可以托管AI Agent的云服务平台可能更符合需求，因为它可以提供更大的灵活性和扩展性。","position":{"start":{"line":9,"column":1},"end":{"line":9,"column":1}},"key":"wSAreb69XC"}],"key":"OWQ8vIKxrw"}],"key":"vgPHL8aGNb"}],"key":"d3bb8E2ZM1"}],"key":"OuJMrvjECn"}],"key":"Fhnybv6C54"},"references":{"cite":{"order":[],"data":{}}}}